epsie/__init__.py
epsie/_version.py
epsie/chain/__init__.py
epsie/chain/base.py
epsie/chain/chain.py
epsie/chain/chaindata.py
epsie/chain/ptchain.py
epsie/proposals/__init__.py
epsie/proposals/angular.py
epsie/proposals/base.py
epsie/proposals/birth.py
epsie/proposals/bounded_eigenvector.py
epsie/proposals/bounded_normal.py
epsie/proposals/discrete.py
epsie/proposals/eigenvector.py
epsie/proposals/joint.py
epsie/proposals/nested_transdimensional.py
epsie/proposals/normal.py
epsie/proposals/solid_angle.py
epsie/samplers/__init__.py
epsie/samplers/base.py
epsie/samplers/mhsampler.py
epsie/samplers/ptsampler.py
epsie-1.0.0.dist-info/LICENSE
epsie-1.0.0.dist-info/METADATA
epsie-1.0.0.dist-info/WHEEL
epsie-1.0.0.dist-info/top_level.txt
epsie-1.0.0.dist-info/RECORD
