Metadata-Version: 2.1
Name: epsie
Version: 1.0.0
Summary: An Embarrassingly Parallel Sampler for Inference Estimation.
Home-page: https://cdcapano.github.io/epsie
Author: Collin D. Capano
Author-email: cdcapano@gmail.com
License: UNKNOWN
Platform: UNKNOWN
Classifier: Programming Language :: Python :: 3
Classifier: License :: OSI Approved :: GNU General Public License v3 (GPLv3)
Classifier: Operating System :: OS Independent
Classifier: Intended Audience :: Science/Research
Classifier: Natural Language :: English
Requires-Python: >=3.6
License-File: LICENSE
Requires-Dist: numpy (>=1.17.0)
Requires-Dist: scipy (>=0.16.0)
Requires-Dist: six (>1.10.0)
